avipy/__init__.py
avipy/atmosphere.py
avipy/constants.py
avipy/geo.py
avipy/qty.py
AviPy-0.3.3.dist-info/LICENSE
AviPy-0.3.3.dist-info/METADATA
AviPy-0.3.3.dist-info/WHEEL
AviPy-0.3.3.dist-info/top_level.txt
AviPy-0.3.3.dist-info/RECORD
