Metadata-Version: 2.1
Name: AviPy
Version: 0.3.3
Summary: A package containing useful tools for aviation related code
Author-email: Paolo Stet <paolostet@proton.me>
Project-URL: Homepage, https://github.com/pcs03/AviPy
Classifier: Programming Language :: Python :: 3
Classifier: License :: OSI Approved :: GNU General Public License v3 (GPLv3)
Classifier: Operating System :: OS Independent
Requires-Python: >=3.10
License-File: LICENSE
